{
  "dev": {
    "profile_name": "default",
    "aws_region": "us-east-2",
    "app_function": "app.__init__.app",
    "project_name": "Shift-4-Haystack",
    "s3_bucket": "alpha-dev-zappa",
    "runtime": "python3.8",
    "aws_environment_variables": {
      "LOG_LEVEL": "INFO",
      "HAYSTACK_PROVIDER": "shaystack.providers.db",
      "HAYSTACK_DB": "s3://shaystack/carytown.zinc"
    },
    "exclude": [
      ".*",
      "data",
      "pip*",
      "*csv",
      "*.whl",
      "boto3",
      "botocore"
    ],
    "slim_handler": false
  }
}
